{"Model":[{"Id":37,"Name":"Ladder Assist","ShortName":"LA","CustomerDescription":"Adjuster and Technician meet on site at specified time to perform inspection.","IsActive":true,"OnExternalForm":true,"CreatedBy":"1","CreatedByName":"SYSTEM USER","CreatedOn":"2013-07-19T13:07:34","Duration":90,"HasDescription":false,"HasQuantity":false,"RequiresDate":true,"RequiresPhone":false,"ShowCalendar":true},{"Id":38,"Name":"Ladder Assist with Eagle View","ShortName":"EV","CustomerDescription":"Adjuster and Technician meet on site at specified time to perform inspection.","IsActive":true,"OnExternalForm":false,"CreatedBy":"124","CreatedByName":"Cristina Vielhaber","CreatedOn":"2014-01-17T12:59:36","Duration":10,"HasDescription":false,"HasQuantity":false,"RequiresDate":true,"RequiresPhone":false,"ShowCalendar":false},{"Id":39,"Name":"Direct Inspection","ShortName":"DI","CustomerDescription":"Hancock or adjuster sets appointment time with Insured.  Inspection reporting provided within 48 hours of inspection. ** Insured contact information required**","IsActive":true,"OnExternalForm":true,"CreatedBy":"1","CreatedByName":"SYSTEM USER","CreatedOn":"2013-07-19T13:07:34","Duration":10,"HasDescription":false,"HasQuantity":false,"RequiresDate":false,"RequiresPhone":true,"ShowCalendar":true},{"Id":40,"Name":"Estimate Repair","ShortName":"EST","CustomerDescription":null,"IsActive":true,"OnExternalForm":false,"CreatedBy":"1","CreatedByName":"SYSTEM USER","CreatedOn":"2013-07-19T13:07:34","Duration":30,"HasDescription":false,"HasQuantity":false,"RequiresDate":true,"RequiresPhone":false,"ShowCalendar":false},{"Id":41,"Name":"Tarp Remove & Reset","ShortName":"R&R","CustomerDescription":"Technician removes and resets existing tarp to complete inspection.","IsActive":true,"OnExternalForm":true,"CreatedBy":"1","CreatedByName":"SYSTEM USER","CreatedOn":"2013-07-19T13:07:34","Duration":30,"HasDescription":false,"HasQuantity":false,"RequiresDate":false,"RequiresPhone":true,"ShowCalendar":false},{"Id":42,"Name":"Emergency Tarp","ShortName":"ET","CustomerDescription":"Technician installs emergency tarp, Hancock sets appointment with insured and installs within 48hrs ** Insured information required **","IsActive":true,"OnExternalForm":false,"CreatedBy":"1","CreatedByName":"SYSTEM USER","CreatedOn":"2013-07-19T13:07:34","Duration":30,"HasDescription":false,"HasQuantity":false,"RequiresDate":false,"RequiresPhone":true,"ShowCalendar":false},{"Id":43,"Name":"0 to 150","ShortName":"ET","CustomerDescription":null,"IsActive":true,"OnExternalForm":false,"CreatedBy":"1","CreatedByName":"SYSTEM USER","CreatedOn":"2013-07-19T13:07:34","Duration":30,"HasDescription":false,"HasQuantity":false,"RequiresDate":false,"RequiresPhone":false,"ShowCalendar":false},{"Id":44,"Name":"151 to 250","ShortName":"ET","CustomerDescription":null,"IsActive":true,"OnExternalForm":false,"CreatedBy":"1","CreatedByName":"SYSTEM USER","CreatedOn":"2013-07-19T13:07:34","Duration":30,"HasDescription":false,"HasQuantity":false,"RequiresDate":false,"RequiresPhone":false,"ShowCalendar":false},{"Id":45,"Name":"251 to 400","ShortName":"ET","CustomerDescription":null,"IsActive":true,"OnExternalForm":false,"CreatedBy":"1","CreatedByName":"SYSTEM USER","CreatedOn":"2013-07-19T13:07:34","Duration":30,"HasDescription":false,"HasQuantity":false,"RequiresDate":false,"RequiresPhone":false,"ShowCalendar":false},{"Id":46,"Name":"401 to 600","ShortName":"ET","CustomerDescription":null,"IsActive":true,"OnExternalForm":false,"CreatedBy":"1","CreatedByName":"SYSTEM USER","CreatedOn":"2013-07-19T13:07:34","Duration":30,"HasDescription":false,"HasQuantity":false,"RequiresDate":false,"RequiresPhone":false,"ShowCalendar":false},{"Id":47,"Name":"601 to 800","ShortName":"ET","CustomerDescription":null,"IsActive":true,"OnExternalForm":false,"CreatedBy":"1","CreatedByName":"SYSTEM USER","CreatedOn":"2013-07-19T13:07:34","Duration":30,"HasDescription":false,"HasQuantity":false,"RequiresDate":false,"RequiresPhone":false,"ShowCalendar":false},{"Id":48,"Name":"801 to 1000","ShortName":"ET","CustomerDescription":null,"IsActive":true,"OnExternalForm":false,"CreatedBy":"1","CreatedByName":"SYSTEM USER","CreatedOn":"2013-07-19T13:07:34","Duration":30,"HasDescription":false,"HasQuantity":false,"RequiresDate":false,"RequiresPhone":false,"ShowCalendar":false},{"Id":49,"Name":"1001 to 1500","ShortName":"ET","CustomerDescription":null,"IsActive":true,"OnExternalForm":false,"CreatedBy":"1","CreatedByName":"SYSTEM USER","CreatedOn":"2013-07-19T13:07:34","Duration":30,"HasDescription":false,"HasQuantity":false,"RequiresDate":false,"RequiresPhone":false,"ShowCalendar":false},{"Id":50,"Name":"1501 to 2000","ShortName":"ET","CustomerDescription":null,"IsActive":true,"OnExternalForm":false,"CreatedBy":"1","CreatedByName":"SYSTEM USER","CreatedOn":"2013-07-19T13:07:34","Duration":30,"HasDescription":false,"HasQuantity":false,"RequiresDate":false,"RequiresPhone":false,"ShowCalendar":false},{"Id":51,"Name":"Rope & Harness","ShortName":"R&H","CustomerDescription":null,"IsActive":true,"OnExternalForm":false,"CreatedBy":"1","CreatedByName":"SYSTEM USER","CreatedOn":"2013-07-19T13:07:34","Duration":30,"HasDescription":false,"HasQuantity":false,"RequiresDate":true,"RequiresPhone":false,"ShowCalendar":false},{"Id":52,"Name":"Trip Charge","ShortName":"TC","CustomerDescription":"","IsActive":true,"OnExternalForm":false,"CreatedBy":"1","CreatedByName":"SYSTEM USER","CreatedOn":"2013-07-19T13:07:34","Duration":65,"HasDescription":false,"HasQuantity":false,"RequiresDate":true,"RequiresPhone":false,"ShowCalendar":false},{"Id":53,"Name":"Cancellation","ShortName":"CANC","CustomerDescription":null,"IsActive":true,"OnExternalForm":false,"CreatedBy":"1","CreatedByName":"SYSTEM USER","CreatedOn":"2013-07-19T13:07:34","Duration":30,"HasDescription":false,"HasQuantity":false,"RequiresDate":true,"RequiresPhone":false,"ShowCalendar":false},{"Id":54,"Name":"Other","ShortName":"OTHR","CustomerDescription":null,"IsActive":false,"OnExternalForm":false,"CreatedBy":"1","CreatedByName":"SYSTEM USER","CreatedOn":"2013-07-19T13:07:34","Duration":30,"HasDescription":true,"HasQuantity":false,"RequiresDate":true,"RequiresPhone":false,"ShowCalendar":false},{"Id":55,"Name":"Ladder Lean","ShortName":"Lean","CustomerDescription":"Adjuster and technician meet on site at specified time. Technician provides ladder access to the roof for the adjuster to complete roof inspection.","IsActive":true,"OnExternalForm":true,"CreatedBy":"254","CreatedByName":"Jeana Jones","CreatedOn":"2014-02-18T13:37:53","Duration":30,"HasDescription":false,"HasQuantity":false,"RequiresDate":true,"RequiresPhone":false,"ShowCalendar":true},{"Id":56,"Name":"Ladder Assist with Rope & Harness","ShortName":"LARH","CustomerDescription":null,"IsActive":true,"OnExternalForm":false,"CreatedBy":"254","CreatedByName":"Jeana Jones","CreatedOn":"2014-02-18T13:38:02.383","Duration":30,"HasDescription":false,"HasQuantity":false,"RequiresDate":true,"RequiresPhone":false,"ShowCalendar":false},{"Id":57,"Name":"Board Up with Inspection","ShortName":"BU","CustomerDescription":null,"IsActive":true,"OnExternalForm":false,"CreatedBy":"124","CreatedByName":"Cristina Vielhaber","CreatedOn":"2014-04-11T11:02:34","Duration":30,"HasDescription":false,"HasQuantity":true,"RequiresDate":false,"RequiresPhone":false,"ShowCalendar":false},{"Id":58,"Name":"Multi Unit Ladder Assist","ShortName":"MU","CustomerDescription":null,"IsActive":true,"OnExternalForm":false,"CreatedBy":"124","CreatedByName":"Cristina Vielhaber","CreatedOn":"2015-01-06T12:13:14.25","Duration":30,"HasDescription":false,"HasQuantity":true,"RequiresDate":true,"RequiresPhone":false,"ShowCalendar":false},{"Id":59,"Name":"Ladder 40ft","ShortName":"40","CustomerDescription":null,"IsActive":true,"OnExternalForm":false,"CreatedBy":"124","CreatedByName":"Cristina Vielhaber","CreatedOn":"2014-11-21T14:16:51.647","Duration":30,"HasDescription":false,"HasQuantity":true,"RequiresDate":true,"RequiresPhone":false,"ShowCalendar":false},{"Id":60,"Name":"ITEL Sample","ShortName":"ITEL","CustomerDescription":null,"IsActive":true,"OnExternalForm":false,"CreatedBy":"263","CreatedByName":"Harrison Wagener","CreatedOn":"2014-04-18T16:10:59.987","Duration":30,"HasDescription":false,"HasQuantity":false,"RequiresDate":true,"RequiresPhone":false,"ShowCalendar":false},{"Id":61,"Name":"Wisconsin Ladder Assist","ShortName":"WILA","CustomerDescription":null,"IsActive":false,"OnExternalForm":false,"CreatedBy":"124","CreatedByName":"Cristina Vielhaber","CreatedOn":"2016-02-12T15:45:55.03","Duration":30,"HasDescription":false,"HasQuantity":false,"RequiresDate":false,"RequiresPhone":false,"ShowCalendar":false}],"Pager":{"CurrentPage":1,"TotalPages":5,"PageSize":25,"TotalCount":110,"NextPage":"https://localhost:44311/api/AvailableServiceTypes?pageNumber=2&pageSize=25","PreviousPage":null}}